hx711-gpiozero/__init__.py
hx711_gpiozero/__init__.py
hx711_gpiozero-0.0.3.dist-info/LICENSE
hx711_gpiozero-0.0.3.dist-info/METADATA
hx711_gpiozero-0.0.3.dist-info/WHEEL
hx711_gpiozero-0.0.3.dist-info/top_level.txt
hx711_gpiozero-0.0.3.dist-info/RECORD
