Metadata-Version: 2.1
Name: hx711-gpiozero
Version: 0.0.3
Summary: A HX711 Driver
Home-page: https://github.com/cyrusn/hx711_gpiozero
Author: CyrusN
Author-email: cyrusncy@gmail.com
License: UNKNOWN
Platform: UNKNOWN
Classifier: Programming Language :: Python :: 3
Classifier: License :: OSI Approved :: MIT License
Classifier: Operating System :: OS Independent
Requires-Python: >=3.7
